rofify/__init__.py
rofify/__main__.py
rofify/src/AlbumMenu.py
rofify/src/ArtistMenu.py
rofify/src/DeviceControls.py
rofify/src/DeviceMenu.py
rofify/src/DynamicNestedMenu.py
rofify/src/Hotkeys.py
rofify/src/MainMenu.py
rofify/src/PlaybackControls.py
rofify/src/PlaybackMenu.py
rofify/src/PlaylistMenu.py
rofify/src/RecentlyPlayedMenu.py
rofify/src/SavedTracksMenu.py
rofify/src/SearchMenu.py
rofify/src/SpotifyAPI.py
rofify/src/TrackMenu.py
rofify/src/__init__.py
rofify/src/config.py
rofify/src/utils.py
rofify-0.0.41.dist-info/LICENSE.txt
rofify-0.0.41.dist-info/METADATA
rofify-0.0.41.dist-info/WHEEL
rofify-0.0.41.dist-info/top_level.txt
rofify-0.0.41.dist-info/RECORD
