Metadata-Version: 2.1
Name: rofify
Version: 0.0.41
Summary: Rofi menu script that controls spotify playback.
Home-page: https://github.com/dbkosky/rofify.git
Author: Daniel Kosky
Author-email: dbkosky@gmail.com
License: MIT
Keywords: spotify,rofi
Classifier: Programming Language :: Python :: 3
Classifier: Programming Language :: Python :: 3.9
Classifier: License :: OSI Approved :: MIT License
License-File: LICENSE.txt
Requires-Dist: spotipy >=2.7.0
Requires-Dist: spotipy <=2.18.0
Requires-Dist: rofi-menu >=0.5.1
Requires-Dist: rofi-menu <=0.6
